requests_etag/__init__.py
requests_etag-1.0.0.dist-info/LICENSE
requests_etag-1.0.0.dist-info/METADATA
requests_etag-1.0.0.dist-info/WHEEL
requests_etag-1.0.0.dist-info/top_level.txt
requests_etag-1.0.0.dist-info/RECORD
