Metadata-Version: 2.1
Name: requests-etag
Version: 1.0.0
Summary: Wrapper over requests package to support etag caching by default
Home-page: https://github.com/sandbox-pokhara/requests-etag
Author: Pradish Bijukchhe
Author-email: pradishbijukchhe@gmail.com
Project-URL: Bug Tracker, https://github.com/sandbox-pokhara/requests-etag/issues
Classifier: Programming Language :: Python :: 3
Classifier: License :: OSI Approved :: MIT License
Classifier: Operating System :: Microsoft :: Windows
Requires-Python: >=3
License-File: LICENSE
Requires-Dist: requests
